LICENSE.md
MANIFEST.in
README.md
setup.cfg
setup.py
netboxapi/__init__.py
netboxapi/api.py
netboxapi/exceptions.py
netboxapi/mapper.py
netboxapi.egg-info/PKG-INFO
netboxapi.egg-info/SOURCES.txt
netboxapi.egg-info/dependency_links.txt
netboxapi.egg-info/requires.txt
netboxapi.egg-info/top_level.txt