Metadata-Version: 1.1
Name: netboxapi
Version: 1.1.6
Summary: Client API for Netbox
Home-page: UNKNOWN
Author: Anthony25 <Anthony Ruhier>
Author-email: anthony.ruhier@gmail.com
License: Simplified BSD
Keywords: netbox,api
Platform: UNKNOWN
Classifier: Programming Language :: Python :: 3 :: Only
Classifier: License :: OSI Approved :: BSD License
